lastochka/__init__.py
lastochka/core/__init__.py
lastochka/core/functions.py
lastochka/core/main.py
lastochka/core/optimizer.py
lastochka-0.0.16.dist-info/LICENSE
lastochka-0.0.16.dist-info/METADATA
lastochka-0.0.16.dist-info/WHEEL
lastochka-0.0.16.dist-info/top_level.txt
lastochka-0.0.16.dist-info/RECORD
