Metadata-Version: 2.1
Name: lastochka
Version: 0.0.16
Summary: Lastochka - Weight Of Evidence Transformer
Home-page: UNKNOWN
Author: Trusov Ivan
Author-email: UNKNOWN
License: UNKNOWN
Platform: UNKNOWN
Requires-Dist: numpy
Requires-Dist: pandas
Requires-Dist: scikit-learn
Requires-Dist: tqdm
